<?xml version="1.0" encoding="UTF-8"?>
<objects serializationModel="Studio.02.02.00">
	<object class="AudioFile" id="{38ad2148-e39f-4edf-bb43-761c4d9550e9}">
		<property name="assetPath">
			<value>Player Movement/Footsteps/Wood/Walk/Carpet/Footsteps-Wood-Carpet-005.wav</value>
		</property>
		<property name="frequencyInKHz">
			<value>48</value>
		</property>
		<property name="channelCount">
			<value>1</value>
		</property>
		<property name="length">
			<value>0.37043749999999998</value>
		</property>
		<relationship name="masterAssetFolder">
			<destination>{e3622c02-0689-434d-9688-3e1530eb1182}</destination>
		</relationship>
	</object>
</objects>
